xclient/__init__.py
xclient/client.py
xclient/models/__init__.py
xclient/models/actions.py
xclient/models/error.py
xclient/models/timeline.py
xclient/models/timestamp.py
xclient/models/tweet.py
xclient/models/user.py
x_api_client-0.0.1.dist-info/METADATA
x_api_client-0.0.1.dist-info/WHEEL
x_api_client-0.0.1.dist-info/licenses/LICENSE
x_api_client-0.0.1.dist-info/RECORD
