Metadata-Version: 2.4
Name: x-api-client
Version: 0.0.1
Summary: A Python client for the public X API.
Project-URL: Homepage, https://github.com/joeychilson/x-client
Project-URL: Documentation, https://github.com/joeychilson/x-client/blob/main/README.md
Project-URL: Repository, https://github.com/joeychilson/x-client.git
Project-URL: Issues, https://github.com/joeychilson/x-client/issues
Author-email: Joey Chilson <joeychilson@outlook.com>
License: MIT License
License-File: LICENSE
Classifier: Development Status :: 3 - Alpha
Classifier: License :: OSI Approved :: MIT License
Classifier: Programming Language :: Python
Classifier: Programming Language :: Python :: 3
Classifier: Programming Language :: Python :: 3 :: Only
Classifier: Programming Language :: Python :: 3.9
Classifier: Programming Language :: Python :: 3.10
Classifier: Programming Language :: Python :: 3.11
Classifier: Programming Language :: Python :: 3.12
Classifier: Programming Language :: Python :: 3.13
Requires-Python: >=3.9
Requires-Dist: httpx>=0.27.2
Requires-Dist: pydantic>=2.10.0
